hotspotyolo/__init__.py
hotspotyolo/activations_and_gradients.py
hotspotyolo/heatmap.py
hotspotyolo/targets.py
hotspotyolo/utils.py
hotspotyolo-0.1.1.dist-info/licenses/LICENSE
tests/__init__.py
tests/test_heatmap.py
hotspotyolo-0.1.1.dist-info/METADATA
hotspotyolo-0.1.1.dist-info/WHEEL
hotspotyolo-0.1.1.dist-info/top_level.txt
hotspotyolo-0.1.1.dist-info/RECORD
