Metadata-Version: 2.4
Name: hotspotyolo
Version: 0.1.1
Summary: Generate CAMs of Yolo Models
Home-page: 
Author: Atharva Hude
Author-email: Atharva Hude <ahude@asu.edu>
License: MIT
Classifier: Programming Language :: Python :: 3
Classifier: License :: OSI Approved :: MIT License
Classifier: Operating System :: OS Independent
Requires-Python: >=3.6
License-File: LICENSE
Dynamic: author
Dynamic: license-file
Dynamic: requires-python
